pcaconcat/__init__.py
pcaconcat/pcaconcat.py
pcaconcat-0.0.3.dist-info/LICENSE
pcaconcat-0.0.3.dist-info/METADATA
pcaconcat-0.0.3.dist-info/WHEEL
pcaconcat-0.0.3.dist-info/dependency_links.txt
pcaconcat-0.0.3.dist-info/top_level.txt
pcaconcat-0.0.3.dist-info/RECORD
