Metadata-Version: 2.1
Name: pcaconcat
Version: 0.0.3
Summary: To merge different pcas in different tables using Python.
Home-page: https://github.com/advancehs/pcaconcat
Author: advancehs
Author-email: 1019753743@qq.com
License: MIT license
Keywords: pcaconcat
Classifier: Development Status :: 2 - Pre-Alpha
Classifier: Intended Audience :: Developers
Classifier: License :: OSI Approved :: MIT License
Classifier: Natural Language :: English
Classifier: Programming Language :: Python :: 3
Classifier: Programming Language :: Python :: 3.7
Classifier: Programming Language :: Python :: 3.8
Classifier: Programming Language :: Python :: 3.9
Classifier: Programming Language :: Python :: 3.10
Requires-Python: >=3.7
License-File: LICENSE
Requires-Dist: addana
Requires-Dist: pandas
Requires-Dist: numpy
